pydb_conn/__init__.py
pydb_conn/sql_server.py
pydb_conn/utils.py
pydb_conn-1.0.2.dist-info/LICENCE
pydb_conn-1.0.2.dist-info/METADATA
pydb_conn-1.0.2.dist-info/WHEEL
pydb_conn-1.0.2.dist-info/top_level.txt
pydb_conn-1.0.2.dist-info/RECORD
